kivy_garden/filebrowser/__init__.py
kivy_garden/filebrowser/_version.py
kivy_garden/filebrowser/tests/test_import.py
kivy_garden.filebrowser-1.1.2.dist-info/AUTHORS.txt
kivy_garden.filebrowser-1.1.2.dist-info/LICENSE.txt
kivy_garden.filebrowser-1.1.2.dist-info/METADATA
kivy_garden.filebrowser-1.1.2.dist-info/WHEEL
kivy_garden.filebrowser-1.1.2.dist-info/top_level.txt
kivy_garden.filebrowser-1.1.2.dist-info/RECORD
