Metadata-Version: 2.1
Name: kivy_garden.filebrowser
Version: 1.1.2
Summary: An advanced kivy file browser.
Home-page: https://github.com/kivy-garden/filebrowser
Author: Kivy
Author-email: kivy@kivy.org
License: UNKNOWN
Project-URL: Bug Reports, https://github.com/kivy-garden/filebrowser/issues
Project-URL: Source, https://github.com/kivy-garden/filebrowser
Keywords: Kivy kivy-garden
Platform: UNKNOWN
Classifier: Development Status :: 4 - Beta
Classifier: Intended Audience :: Developers
Classifier: Topic :: Software Development :: Libraries
Classifier: License :: OSI Approved :: MIT License
Classifier: Programming Language :: Python :: 3.5
Classifier: Programming Language :: Python :: 3.6
Classifier: Programming Language :: Python :: 3.7
Classifier: Programming Language :: Python :: 3.8
Provides-Extra: ci
Provides-Extra: dev
